bankroll/brokers/ibkr/__init__.py
bankroll/brokers/ibkr/account.py
bankroll/brokers/ibkr/py.typed
bankroll_broker_ibkr-0.4.0.dist-info/LICENSE
bankroll_broker_ibkr-0.4.0.dist-info/METADATA
bankroll_broker_ibkr-0.4.0.dist-info/WHEEL
bankroll_broker_ibkr-0.4.0.dist-info/top_level.txt
bankroll_broker_ibkr-0.4.0.dist-info/RECORD
